cleantxt/__init__.py
cleantxt/__main__.py
cleantxt/text.py
cleantxt-0.0.7.dist-info/LICENSE
cleantxt-0.0.7.dist-info/METADATA
cleantxt-0.0.7.dist-info/WHEEL
cleantxt-0.0.7.dist-info/entry_points.txt
cleantxt-0.0.7.dist-info/top_level.txt
cleantxt-0.0.7.dist-info/RECORD
