Metadata-Version: 2.1
Name: cleantxt
Version: 0.0.7
Summary: cleaning text from noise for nlp tasks
Home-page: https://github.com/jemiaymen/cleantxt
Author: Aymen Jemi
Author-email: jemiaymen@gmail.com
License: UNKNOWN
Project-URL: Bug Tracker, https://github.com/jemiaymen/cleantxt/issues
Platform: UNKNOWN
Classifier: Programming Language :: Python :: 3
Classifier: License :: OSI Approved :: MIT License
Classifier: Operating System :: OS Independent
Requires-Python: >=3.6
Requires-Dist: tqdm
